ubai_client/__init__.py
ubai_client/api_client.py
ubai_client/configuration.py
ubai_client/exceptions.py
ubai_client/model_utils.py
ubai_client/rest.py
ubai_client/api/__init__.py
ubai_client/api/artifact_api.py
ubai_client/api/search_api.py
ubai_client/apis/__init__.py
ubai_client/model/__init__.py
ubai_client/model/artifact_input.py
ubai_client/model/artifact_metadata.py
ubai_client/model/artifact_storage.py
ubai_client/model/http_validation_error.py
ubai_client/model/num_updated_artifacts.py
ubai_client/model/validation_error.py
ubai_client/models/__init__.py
ubai_client-1.2.1.dist-info/METADATA
ubai_client-1.2.1.dist-info/WHEEL
ubai_client-1.2.1.dist-info/top_level.txt
ubai_client-1.2.1.dist-info/RECORD
